djangovirtualpos/__init__.py
djangovirtualpos/__version__.py
djangovirtualpos/admin.py
djangovirtualpos/debug.py
djangovirtualpos/fields.py
djangovirtualpos/forms.py
djangovirtualpos/models.py
djangovirtualpos/urls.py
djangovirtualpos/util.py
djangovirtualpos/views.py
djangovirtualpos/migrations/0001_initial.py
djangovirtualpos/migrations/0002_vpospaymentoperation_response_code.py
djangovirtualpos/migrations/0003_auto_20170310_1829.py
djangovirtualpos/migrations/0004_auto_20170313_1401.py
djangovirtualpos/migrations/0005_auto_20170314_1057.py
djangovirtualpos/migrations/0006_vpospaymentoperation_environment.py
djangovirtualpos/migrations/0007_auto_20170320_1757.py
djangovirtualpos/migrations/0008_auto_20170321_1437.py
djangovirtualpos/migrations/0009_vpsrefundoperation.py
djangovirtualpos/migrations/0010_auto_20170329_1227.py
djangovirtualpos/migrations/0011_auto_20170404_1424.py
djangovirtualpos/migrations/0012_auto_20180209_1222.py
djangovirtualpos/migrations/0013_vposredsys_enable_preauth_policy.py
djangovirtualpos/migrations/0014_auto_20180403_1057.py
djangovirtualpos/migrations/__init__.py
djangovirtualpos/templatetags/__init__.py
djangovirtualpos/templatetags/djangovirtualpos_js.py
django_virtual_pos-1.7.1.dist-info/LICENSE
django_virtual_pos-1.7.1.dist-info/METADATA
django_virtual_pos-1.7.1.dist-info/WHEEL
django_virtual_pos-1.7.1.dist-info/top_level.txt
django_virtual_pos-1.7.1.dist-info/RECORD
