Metadata-Version: 2.1
Name: django-virtual-pos
Version: 1.7.1
Summary: django-virtual-pos is a module that abstracts the flow of paying in several online payment platforms.
Home-page: https://github.com/intelligenia/django-virtual-pos
Author: intelligenia
Author-email: mario@intelligenia.com
License: MIT
Keywords: virtual,point-of-sale,puchases,online,payments
Platform: UNKNOWN
Classifier: Development Status :: 5 - Production/Stable
Classifier: Framework :: Django
Classifier: License :: OSI Approved :: MIT License
Requires-Python: >=2.7.0
Requires-Dist: beautifulsoup4
Requires-Dist: django
Requires-Dist: lxml
Requires-Dist: pycrypto
Requires-Dist: pytz
Requires-Dist: requests
